{
  "hokkaidou-touhoku": {
    "beers": [
      {
        "name": "hokkaidou-aaa",
        "style": "IPA",
        "color": "#f7851e",
        "alcohol": 5,
        "bitterness": "3",
        "sweetness": "2",
        "full-bodied": "4",
        "feature": "ほんのり甘い香りが〜〜〜〜"
      },
      {
        "name": "hokkaidou-bbb",
        "style": "ピルスナー",
        "color": "#f7851e",
        "alcohol": 7,
        "bitterness": "3",
        "sweetness": "2",
        "full-bodied": "4",
        "feature": "キリッと酸味の〜〜〜〜"
      },
      {
        "name": "hokkaidou-ccc",
        "style": "ペールエール",
        "color": "#f7851e",
        "alcohol": 3,
        "bitterness": "3",
        "sweetness": "2",
        "full-bodied": "4",
        "feature": "程よい苦味の〜〜〜〜"
      }
    ]
  },
  "kantou": {
    "beers": [
      {
        "name": "kantou-aaa",
        "style": "IPA",
        "color": "#f7851e",
        "alcohol": 5,
        "bitterness": "3",
        "sweetness": "2",
        "full-bodied": "4",
        "feature": "ほんのり甘い香りが〜〜〜〜"
      },
      {
        "name": "kantou-bbb",
        "style": "ピルスナー",
        "color": "#f7851e",
        "alcohol": 7,
        "bitterness": "3",
        "sweetness": "2",
        "full-bodied": "4",
        "feature": "キリッと酸味の〜〜〜〜"
      },
      {
        "name": "kantou-ccc",
        "style": "ペールエール",
        "color": "#f7851e",
        "alcohol": 3,
        "bitterness": "3",
        "sweetness": "2",
        "full-bodied": "4",
        "feature": "程よい苦味の〜〜〜〜"
      }
    ]
  },
  "tyubu": {
    "beers": [
      {
        "name": "tyubu-aaa",
        "style": "IPA",
        "color": "#f7851e",
        "alcohol": 5,
        "bitterness": "3",
        "sweetness": "2",
        "full-bodied": "4",
        "feature": "ほんのり甘い香りが〜〜〜〜"
      },
      {
        "name": "tyubu-bbb",
        "style": "ピルスナー",
        "color": "#f7851e",
        "alcohol": 7,
        "bitterness": "3",
        "sweetness": "2",
        "full-bodied": "4",
        "feature": "キリッと酸味の〜〜〜〜"
      },
      {
        "name": "tyubu-ccc",
        "style": "ペールエール",
        "color": "#f7851e",
        "alcohol": 3,
        "bitterness": "3",
        "sweetness": "2",
        "full-bodied": "4",
        "feature": "程よい苦味の〜〜〜〜"
      }
    ]
  },
  "kinki": {
    "beers": [
      {
        "name": "kinki-aaa",
        "style": "IPA",
        "color": "#f7851e",
        "alcohol": 5,
        "bitterness": "3",
        "sweetness": "2",
        "full-bodied": "4",
        "feature": "ほんのり甘い香りが〜〜〜〜"
      },
      {
        "name": "kinki-bbb",
        "style": "ピルスナー",
        "color": "#f7851e",
        "alcohol": 7,
        "bitterness": "3",
        "sweetness": "2",
        "full-bodied": "4",
        "feature": "キリッと酸味の〜〜〜〜"
      },
      {
        "name": "kinki-ccc",
        "style": "ペールエール",
        "color": "#f7851e",
        "alcohol": 3,
        "bitterness": "3",
        "sweetness": "2",
        "full-bodied": "4",
        "feature": "程よい苦味の〜〜〜〜"
      }
    ]
  },
  "tyugoku": {
    "beers": [
      {
        "name": "tyugoku-aaa",
        "style": "IPA",
        "color": "#f7851e",
        "alcohol": 5,
        "bitterness": "3",
        "sweetness": "2",
        "full-bodied": "4",
        "feature": "ほんのり甘い香りが〜〜〜〜"
      },
      {
        "name": "tyugoku-bbb",
        "style": "ピルスナー",
        "color": "#f7851e",
        "alcohol": 7,
        "bitterness": "3",
        "sweetness": "2",
        "full-bodied": "4",
        "feature": "キリッと酸味の〜〜〜〜"
      },
      {
        "name": "tyugoku-ccc",
        "style": "ペールエール",
        "color": "#f7851e",
        "alcohol": 3,
        "bitterness": "3",
        "sweetness": "2",
        "full-bodied": "4",
        "feature": "程よい苦味の〜〜〜〜"
      }
    ]
  },
  "shikoku": {
    "beers": [
      {
        "name": "shikoku-aaa",
        "style": "IPA",
        "color": "#f7851e",
        "alcohol": 5,
        "bitterness": "3",
        "sweetness": "2",
        "full-bodied": "4",
        "feature": "ほんのり甘い香りが〜〜〜〜"
      },
      {
        "name": "shikoku-bbb",
        "style": "ピルスナー",
        "color": "#f7851e",
        "alcohol": 7,
        "bitterness": "3",
        "sweetness": "2",
        "full-bodied": "4",
        "feature": "キリッと酸味の〜〜〜〜"
      },
      {
        "name": "shikoku-ccc",
        "style": "ペールエール",
        "color": "#f7851e",
        "alcohol": 3,
        "bitterness": "3",
        "sweetness": "2",
        "full-bodied": "4",
        "feature": "程よい苦味の〜〜〜〜"
      }
    ]
  },
  "kyusyu": {
    "beers": [
      {
        "name": "kyusyu-aaa",
        "style": "IPA",
        "color": "#f7851e",
        "alcohol": 5,
        "bitterness": "3",
        "sweetness": "2",
        "full-bodied": "4",
        "feature": "ほんのり甘い香りが〜〜〜〜"
      },
      {
        "name": "kyusyu-bbb",
        "style": "ピルスナー",
        "color": "#f7851e",
        "alcohol": 7,
        "bitterness": "3",
        "sweetness": "2",
        "full-bodied": "4",
        "feature": "キリッと酸味の〜〜〜〜"
      },
      {
        "name": "kyusyu-ccc",
        "style": "ペールエール",
        "color": "#f7851e",
        "alcohol": 3,
        "bitterness": "3",
        "sweetness": "2",
        "full-bodied": "4",
        "feature": "程よい苦味の〜〜〜〜"
      }
    ]
  }
}
